napari_exodeepfinder/__init__.py
napari_exodeepfinder/_cluster_widget.py
napari_exodeepfinder/_orthoview_widget.py
napari_exodeepfinder/_reader.py
napari_exodeepfinder/_segmentation_widget.py
napari_exodeepfinder/_widget.py
napari_exodeepfinder/_writer.py
napari_exodeepfinder/napari.yaml
napari_exodeepfinder/_tests/__init__.py
napari_exodeepfinder/_tests/test_reader.py
napari_exodeepfinder/_tests/test_widget.py
napari_exodeepfinder/_tests/test_writer.py
napari_exodeepfinder-0.0.11.dist-info/LICENSE
napari_exodeepfinder-0.0.11.dist-info/METADATA
napari_exodeepfinder-0.0.11.dist-info/WHEEL
napari_exodeepfinder-0.0.11.dist-info/entry_points.txt
napari_exodeepfinder-0.0.11.dist-info/top_level.txt
napari_exodeepfinder-0.0.11.dist-info/RECORD
