Metadata-Version: 2.1
Name: napari-exodeepfinder
Version: 0.0.11
Summary: A napari plugin for the ExpDeepFinder library which includes display, annotation, target generation, segmentation and clustering functionalities. An orthoslice view has been added for an easier visualisation and annotation process.
Home-page: https://github.com/deep-finder/napari-exodeepfinder
Author: Constantin Aronssohn, Arthur Masson
Author-email: cnstt@tutanota.com
License: GPL-3.0-only
Project-URL: Bug Tracker, https://github.com/deep-finder/napari-exodeepfinder/issues
Project-URL: Documentation, https://deep-finder.github.io/napari-exodeepfinder/
Project-URL: Source Code, https://github.com/deep-finder/napari-exodeepfinder
Project-URL: User Support, https://github.com/deep-finder/napari-exodeepfinder/issues
Classifier: Development Status :: 3 - Alpha
Classifier: Intended Audience :: Education
Classifier: Intended Audience :: Science/Research
Classifier: Framework :: napari
Classifier: Topic :: Scientific/Engineering
Classifier: Topic :: Scientific/Engineering :: Visualization
Classifier: Topic :: Scientific/Engineering :: Information Analysis
Classifier: Topic :: Scientific/Engineering :: Bio-Informatics
Classifier: Topic :: Scientific/Engineering :: Artificial Intelligence
Classifier: Topic :: Scientific/Engineering :: Image Processing
Classifier: Programming Language :: Python
Classifier: Programming Language :: Python :: 3
Classifier: Programming Language :: Python :: 3.8
Classifier: Programming Language :: Python :: 3.9
Classifier: Programming Language :: Python :: 3.10
Classifier: Operating System :: OS Independent
Classifier: License :: OSI Approved :: GNU General Public License v3 (GPLv3)
Requires-Python: >=3.9
License-File: LICENSE
Requires-Dist: exodeepfinder>=0.3.11
Requires-Dist: typing>=3.7.4.3
Requires-Dist: pandas>=2.2.2
Requires-Dist: pillow>=10.3.0
Provides-Extra: all
Requires-Dist: napari[all]>=0.4.19; extra == "all"
Provides-Extra: testing
Requires-Dist: tox; extra == "testing"
Requires-Dist: pytest; extra == "testing"
Requires-Dist: pytest-cov; extra == "testing"
Requires-Dist: pytest-qt; extra == "testing"
Requires-Dist: napari[all]>=0.4.19; extra == "testing"
